razorpay_ipn_django_handler/__init__.py
razorpay_ipn_django_handler/admin.py
razorpay_ipn_django_handler/apps.py
razorpay_ipn_django_handler/models.py
razorpay_ipn_django_handler/signals.py
razorpay_ipn_django_handler/tests.py
razorpay_ipn_django_handler/urls.py
razorpay_ipn_django_handler/utilities.py
razorpay_ipn_django_handler/views.py
razorpay_ipn_django_handler/migrations/0001_initial.py
razorpay_ipn_django_handler/migrations/__init__.py
razorpay_ipn_django_handler-1.0.0.dist-info/LICENSE
razorpay_ipn_django_handler-1.0.0.dist-info/METADATA
razorpay_ipn_django_handler-1.0.0.dist-info/WHEEL
razorpay_ipn_django_handler-1.0.0.dist-info/top_level.txt
razorpay_ipn_django_handler-1.0.0.dist-info/RECORD
